cmem_plugin_office365/__init__.py
cmem_plugin_office365/autocompletion.py
cmem_plugin_office365/download.py
cmem_plugin_office365/list.py
cmem_plugin_office365/o365-download.svg
cmem_plugin_office365/o365-list.svg
cmem_plugin_office365/o365-upload.svg
cmem_plugin_office365/retrieval.py
cmem_plugin_office365/upload.py
cmem_plugin_office365-2.2.0.dist-info/METADATA
cmem_plugin_office365-2.2.0.dist-info/WHEEL
cmem_plugin_office365-2.2.0.dist-info/licenses/LICENSE
cmem_plugin_office365-2.2.0.dist-info/RECORD
