Metadata-Version: 2.4
Name: cmem-plugin-office365
Version: 2.2.0
Summary: Extract and process data from your Office365 instance.
License: Apache-2.0
License-File: LICENSE
Keywords: eccenca Corporate Memory,plugin
Author: eccenca GmbH
Author-email: cmempy-developer@eccenca.com
Requires-Python: >=3.13,<4.0
Classifier: Development Status :: 5 - Production/Stable
Classifier: Environment :: Plugins
Classifier: License :: OSI Approved :: Apache Software License
Classifier: Programming Language :: Python :: 3
Classifier: Programming Language :: Python :: 3.13
Classifier: Programming Language :: Python :: 3.14
Requires-Dist: cmem-plugin-base (>=4.15.0,<5.0.0)
Requires-Dist: office365-rest-python-client (>=2.6.2,<3.0.0)
